LICENSE.txt
MANIFEST.in
README.md
setup.py
tk_cbed/__init__.py
tk_cbed/model.py
tk_cbed/tk_cbed.py
tk_cbed/version.py
tk_cbed.egg-info/PKG-INFO
tk_cbed.egg-info/SOURCES.txt
tk_cbed.egg-info/dependency_links.txt
tk_cbed.egg-info/requires.txt
tk_cbed.egg-info/top_level.txt
tk_cbed/models/c_cbed.h5
tk_cbed/models/r_cbed.h5
tk_cbed/models/rc_cbed.h5
tk_cbed/test_data/cbed.h5